{
  "version": "1.0",
  "description": "Common first names — biased for recognition, disambiguated from tech homophones.",
  "terms": [
    { "term": "Aaron", "category": "name", "aliases": ["aaron"] },
    { "term": "Adam", "category": "name", "aliases": ["adam"] },
    { "term": "Alan", "category": "name", "aliases": ["alan"] },
    { "term": "Alex", "category": "name", "aliases": ["alex"] },
    { "term": "Alexander", "category": "name", "aliases": ["alexander"] },
    { "term": "Amanda", "category": "name", "aliases": ["amanda"] },
    { "term": "Amy", "category": "name", "aliases": ["amy"] },
    { "term": "Andrew", "category": "name", "aliases": ["andrew"] },
    { "term": "Angela", "category": "name", "aliases": ["angela"] },
    { "term": "Anna", "category": "name", "aliases": ["anna"] },
    { "term": "Anthony", "category": "name", "aliases": ["anthony"] },
    { "term": "Ashley", "category": "name", "aliases": ["ashley"] },
    { "term": "Austin", "category": "name", "aliases": ["austin"] },
    { "term": "Benjamin", "category": "name", "aliases": ["benjamin", "ben"] },
    { "term": "Brandon", "category": "name", "aliases": ["brandon"] },
    { "term": "Brian", "category": "name", "aliases": ["brian"] },
    { "term": "Bruce", "category": "name", "aliases": ["bruce"] },
    { "term": "Carl", "category": "name", "aliases": ["carl"] },
    { "term": "Charles", "category": "name", "aliases": ["charles", "charlie"] },
    { "term": "Chris", "category": "name", "aliases": ["chris"] },
    { "term": "Christopher", "category": "name", "aliases": ["christopher"] },
    { "term": "Daniel", "category": "name", "aliases": ["daniel", "dan"] },
    { "term": "David", "category": "name", "aliases": ["david", "dave"] },
    { "term": "Dennis", "category": "name", "aliases": ["dennis"] },
    { "term": "Donald", "category": "name", "aliases": ["donald", "don"] },
    { "term": "Douglas", "category": "name", "aliases": ["douglas", "doug"] },
    { "term": "Dylan", "category": "name", "aliases": ["dylan"] },
    { "term": "Edward", "category": "name", "aliases": ["edward", "ed", "eddie"] },
    { "term": "Elizabeth", "category": "name", "aliases": ["elizabeth", "liz", "beth"] },
    { "term": "Emily", "category": "name", "aliases": ["emily"] },
    { "term": "Eric", "category": "name", "aliases": ["eric"] },
    { "term": "Ethan", "category": "name", "aliases": ["ethan"] },
    { "term": "Frank", "category": "name", "aliases": ["frank"] },
    { "term": "Gabriel", "category": "name", "aliases": ["gabriel", "gabe"] },
    { "term": "Gary", "category": "name", "aliases": ["gary"] },
    { "term": "George", "category": "name", "aliases": ["george"] },
    { "term": "Gregory", "category": "name", "aliases": ["gregory", "greg"] },
    { "term": "Harold", "category": "name", "aliases": ["harold", "harry"] },
    { "term": "Henry", "category": "name", "aliases": ["henry"] },
    { "term": "Jack", "category": "name", "aliases": ["jack"] },
    { "term": "Jackson", "category": "name", "aliases": ["jackson"] },
    { "term": "Jacob", "category": "name", "aliases": ["jacob", "jake"] },
    { "term": "James", "category": "name", "aliases": ["james", "jim", "jimmy"] },
    { "term": "Jason", "category": "name", "aliases": ["jason"], "conflicts": ["JSON"] },
    { "term": "Jeffrey", "category": "name", "aliases": ["jeffrey", "jeff"] },
    { "term": "Jennifer", "category": "name", "aliases": ["jennifer", "jen"] },
    { "term": "Jeremy", "category": "name", "aliases": ["jeremy"] },
    { "term": "Jerry", "category": "name", "aliases": ["jerry"] },
    { "term": "Jessica", "category": "name", "aliases": ["jessica", "jess"] },
    { "term": "John", "category": "name", "aliases": ["john", "jon"] },
    { "term": "Jonathan", "category": "name", "aliases": ["jonathan"] },
    { "term": "Jordan", "category": "name", "aliases": ["jordan"] },
    { "term": "Joseph", "category": "name", "aliases": ["joseph", "joe"] },
    { "term": "Joshua", "category": "name", "aliases": ["joshua", "josh"] },
    { "term": "Justin", "category": "name", "aliases": ["justin"] },
    { "term": "Karen", "category": "name", "aliases": ["karen"] },
    { "term": "Katherine", "category": "name", "aliases": ["katherine", "kate", "katie"] },
    { "term": "Keith", "category": "name", "aliases": ["keith"] },
    { "term": "Kenneth", "category": "name", "aliases": ["kenneth", "ken"] },
    { "term": "Kevin", "category": "name", "aliases": ["kevin"] },
    { "term": "Kyle", "category": "name", "aliases": ["kyle"] },
    { "term": "Larry", "category": "name", "aliases": ["larry"] },
    { "term": "Laura", "category": "name", "aliases": ["laura"] },
    { "term": "Lauren", "category": "name", "aliases": ["lauren"] },
    { "term": "Lawrence", "category": "name", "aliases": ["lawrence", "larry"] },
    { "term": "Lisa", "category": "name", "aliases": ["lisa"] },
    { "term": "Logan", "category": "name", "aliases": ["logan"] },
    { "term": "Louis", "category": "name", "aliases": ["louis", "lewis"] },
    { "term": "Mark", "category": "name", "aliases": ["mark"] },
    { "term": "Mary", "category": "name", "aliases": ["mary"] },
    { "term": "Matthew", "category": "name", "aliases": ["matthew", "matt"] },
    { "term": "Megan", "category": "name", "aliases": ["megan"] },
    { "term": "Michael", "category": "name", "aliases": ["michael", "mike"] },
    { "term": "Michelle", "category": "name", "aliases": ["michelle"] },
    { "term": "Nancy", "category": "name", "aliases": ["nancy"] },
    { "term": "Nathan", "category": "name", "aliases": ["nathan", "nate"] },
    { "term": "Nicholas", "category": "name", "aliases": ["nicholas", "nick"] },
    { "term": "Nicole", "category": "name", "aliases": ["nicole"] },
    { "term": "Noah", "category": "name", "aliases": ["noah"] },
    { "term": "Patrick", "category": "name", "aliases": ["patrick", "pat"] },
    { "term": "Paul", "category": "name", "aliases": ["paul"] },
    { "term": "Peter", "category": "name", "aliases": ["peter", "pete"] },
    { "term": "Philip", "category": "name", "aliases": ["philip", "phil"] },
    { "term": "Rachel", "category": "name", "aliases": ["rachel"] },
    { "term": "Raymond", "category": "name", "aliases": ["raymond", "ray"] },
    { "term": "Rebecca", "category": "name", "aliases": ["rebecca", "becky"] },
    { "term": "Richard", "category": "name", "aliases": ["richard", "rick", "rich"] },
    { "term": "Robert", "category": "name", "aliases": ["robert", "rob", "bob", "bobby"] },
    { "term": "Roger", "category": "name", "aliases": ["roger"] },
    { "term": "Ronald", "category": "name", "aliases": ["ronald", "ron"] },
    { "term": "Ryan", "category": "name", "aliases": ["ryan"] },
    { "term": "Samuel", "category": "name", "aliases": ["samuel", "sam"] },
    { "term": "Sandra", "category": "name", "aliases": ["sandra", "sandy"] },
    { "term": "Sarah", "category": "name", "aliases": ["sarah", "sara"] },
    { "term": "Scott", "category": "name", "aliases": ["scott"] },
    { "term": "Sean", "category": "name", "aliases": ["sean", "shawn"] },
    { "term": "Stephanie", "category": "name", "aliases": ["stephanie", "steph"] },
    { "term": "Stephen", "category": "name", "aliases": ["stephen", "steve"] },
    { "term": "Steven", "category": "name", "aliases": ["steven", "steve"] },
    { "term": "Susan", "category": "name", "aliases": ["susan", "sue"] },
    { "term": "Teresa", "category": "name", "aliases": ["teresa"] },
    { "term": "Thomas", "category": "name", "aliases": ["thomas", "tom", "tommy"] },
    { "term": "Timothy", "category": "name", "aliases": ["timothy", "tim"] },
    { "term": "Tyler", "category": "name", "aliases": ["tyler"] },
    { "term": "Victoria", "category": "name", "aliases": ["victoria", "vicky"] },
    { "term": "Vincent", "category": "name", "aliases": ["vincent", "vince"] },
    { "term": "Walter", "category": "name", "aliases": ["walter", "walt"] },
    { "term": "William", "category": "name", "aliases": ["william", "will", "bill", "billy"] },
    { "term": "Zachary", "category": "name", "aliases": ["zachary", "zach"] }
  ]
}
